<scene name="intro-6" layout="default" sceneDirector="play.py">
  <sceneDirector nextScene="menu"/>
  <layer name="main">
    <actor costume="stars2" x="400.0" y="300.0" id="" colorize=""/>
    <text x="392.0" y="19.0" zOrder="3" id="" font="Vera" fontSize="26.0" text="You've completed the introduction..." color="#ffffffff" colorize="" makeup="uk.co.nickthecoder.itchy.makeup.Textured">
      <makeup/>
    </text>
    <actor costume="ship2" x="452.0" y="184.0" heading="90.0" zOrder="13" id="" direction="90.0" colorize="" role="ship.py"/>
    <actor costume="scala-a" x="630.0" y="496.0" zOrder="15" id="" colorize="" role="rock.py">
      <role strength="1.0" rotationSpeed="-1.5" vx="-2.0" vy="0.05"/>
    </actor>
    <actor costume="java-0" x="131.0" y="486.0" zOrder="16" id="" colorize="" role="rock.py">
      <role strength="1.0" rotationSpeed="0.2" vx="0.3" vy="0.8"/>
    </actor>
    <actor costume="duke-0" x="126.0" y="183.0" zOrder="17" id="" colorize="" role="rock.py">
      <role strength="1.0" rotationSpeed="-1.0" vx="0.1" vy="0.8"/>
    </actor>
    <actor costume="python-a" x="267.0" y="342.0" zOrder="18" id="" colorize="" role="rock.py">
      <role strength="1.0" rotationSpeed="1.0" vx="1.0" vy="0.3"/>
    </actor>
  </layer>
  <layer name="foreground"/>
</scene>
