<scene name="level04" layout="default" sceneDirector="uk.co.nickthecoder.drunkinvaders.Level">
  <layer name="background">
    <actor costume="earth1" x="320.0" y="240.0" zOrder="1" id="" colorize=""/>
  </layer>
  <layer name="main">
    <actor costume="ship" x="183.0" y="183.0" heading="45.0" zOrder="2" id="" direction="45.0" colorize="" role="uk.co.nickthecoder.drunkinvaders.Ship">
      <role vx="0.0" vy="0.0" mass="1.0" ox="0.0" oy="0.0" rotationSpeed="0.012" shieldRechargeRate="0.001" shieldDischargeRate="0.01"/>
    </actor>
    <actor costume="factory" x="65.0" y="431.0" zOrder="3" id="" colorize="" role="uk.co.nickthecoder.drunkinvaders.AlienFactory">
      <role costumeName="alien1" delayPerAlien="0.5" alienCount="7" spacing="80.0" fireOnceEvery="6.0"/>
    </actor>
    <actor costume="factory" x="65.0" y="385.0" zOrder="4" id="" colorize="" role="uk.co.nickthecoder.drunkinvaders.AlienFactory">
      <role costumeName="alien2" delayPerAlien="0.5" alienCount="7" spacing="80.0" fireOnceEvery="8.0"/>
    </actor>
    <actor costume="factory" x="68.0" y="334.0" zOrder="5" id="" colorize="" role="uk.co.nickthecoder.drunkinvaders.AlienFactory">
      <role costumeName="alien3" delayPerAlien="0.5" alienCount="7" spacing="80.0" fireOnceEvery="10.0"/>
    </actor>
  </layer>
</scene>
