<scene showMouse="false" role="level.py" background="#000000ff">
  <properties/>
  <layer name="grid">
    <actor costume="warp" x="-1200" y="-360" direction="0.0" heading="0.0" startEvent="default" zOrder="7">
      <property name="exitX" value="0"/>
      <property name="exitY" value="-1"/>
      <property name="scene" value="balloons5"/>
    </actor>
    <actor costume="wall" x="-180" y="360" direction="0.0" heading="0.0" startEvent="default" zOrder="8"/>
    <actor costume="wall" x="60" y="420" direction="0.0" heading="0.0" startEvent="default" zOrder="9"/>
    <actor costume="wall" x="-120" y="0" direction="0.0" heading="0.0" startEvent="default" zOrder="11"/>
    <actor costume="wall" x="-120" y="-120" direction="0.0" heading="0.0" startEvent="default" zOrder="19"/>
    <actor costume="wall" x="180" y="360" direction="0.0" heading="0.0" startEvent="default" zOrder="20"/>
    <actor costume="wall" x="180" y="420" direction="0.0" heading="0.0" startEvent="default" zOrder="21"/>
    <actor costume="wall" x="120" y="420" direction="0.0" heading="0.0" startEvent="default" zOrder="22"/>
    <actor costume="wall" x="0" y="420" direction="0.0" heading="0.0" startEvent="default" zOrder="25"/>
    <actor costume="wall" x="-60" y="-180" direction="0.0" heading="0.0" startEvent="default" zOrder="26"/>
    <actor costume="wall" x="120" y="0" direction="0.0" heading="0.0" startEvent="default" zOrder="27"/>
    <actor costume="wall" x="240" y="240" direction="0.0" heading="0.0" startEvent="default" zOrder="28"/>
    <actor costume="wall" x="60" y="180" direction="0.0" heading="0.0" startEvent="default" zOrder="29"/>
    <actor costume="wall" x="120" y="120" direction="0.0" heading="0.0" startEvent="default" zOrder="31"/>
    <actor costume="wall" x="-60" y="180" direction="0.0" heading="0.0" startEvent="default" zOrder="32"/>
    <actor costume="wall" x="-60" y="420" direction="0.0" heading="0.0" startEvent="default" zOrder="45"/>
    <actor costume="wall" x="-120" y="420" direction="0.0" heading="0.0" startEvent="default" zOrder="46"/>
    <actor costume="wall" x="-180" y="420" direction="0.0" heading="0.0" startEvent="default" zOrder="47"/>
    <actor costume="wall" x="720" y="360" direction="0.0" heading="0.0" startEvent="default" zOrder="49"/>
    <actor costume="wall" x="120" y="-120" direction="0.0" heading="0.0" startEvent="default" zOrder="51"/>
    <actor costume="wall" x="60" y="-180" direction="0.0" heading="0.0" startEvent="default" zOrder="56"/>
    <actor costume="wall" x="480" y="300" direction="0.0" heading="0.0" startEvent="default" zOrder="57"/>
    <actor costume="wall" x="540" y="300" direction="0.0" heading="0.0" startEvent="default" zOrder="62"/>
    <actor costume="wall" x="840" y="240" direction="0.0" heading="0.0" startEvent="default" zOrder="75"/>
    <actor costume="wall" x="600" y="180" direction="0.0" heading="0.0" startEvent="default" zOrder="78"/>
    <actor costume="warp" x="0" y="-60" direction="0.0" heading="0.0" startEvent="default" zOrder="188">
      <property name="exitX" value="0"/>
      <property name="exitY" value="-1"/>
      <property name="scene" value="intro"/>
    </actor>
    <actor costume="warp" x="0" y="-300" direction="0.0" heading="0.0" startEvent="default" zOrder="189">
      <property name="exitX" value="0"/>
      <property name="exitY" value="-1"/>
      <property name="scene" value="combined"/>
    </actor>
    <actor costume="warp" x="-240" y="-120" direction="0.0" heading="0.0" startEvent="default" zOrder="190">
      <property name="exitX" value="0"/>
      <property name="exitY" value="-1"/>
      <property name="scene" value="balloons"/>
    </actor>
    <actor costume="warp" x="240" y="120" direction="0.0" heading="0.0" startEvent="default" zOrder="191">
      <property name="exitX" value="0"/>
      <property name="exitY" value="1"/>
      <property name="scene" value="grenades"/>
    </actor>
    <text text="Intro" font="Boycott" size="22" color="#ffffff" xAlignment="0.5" yAlignment="0.5" x="0" y="-60" direction="0.0" heading="0.0" startEvent="default" zOrder="192">
      <makeup classname="uk.co.nickthecoder.itchy.makeup.Shadow">
        <property name="dx" value="2"/>
        <property name="dy" value="-1"/>
        <property name="color" value="#000000ff"/>
      </makeup>
    </text>
    <actor costume="wallNE" x="120" y="180" direction="0.0" heading="0.0" startEvent="default" zOrder="193"/>
    <actor costume="wallNW" x="-120" y="180" direction="0.0" heading="0.0" startEvent="default" zOrder="194"/>
    <actor costume="wallSE" x="120" y="-180" direction="0.0" heading="0.0" startEvent="default" zOrder="195"/>
    <actor costume="wallSW" x="-120" y="-180" direction="0.0" heading="0.0" startEvent="default" zOrder="196"/>
    <actor costume="arrowKeys" x="0" y="16" direction="0.0" heading="0.0" startEvent="default" zOrder="197"/>
    <actor costume="wall" x="-120" y="120" direction="0.0" heading="0.0" startEvent="default" zOrder="198"/>
    <actor costume="portcullis" x="-120" y="-60" direction="0.0" heading="0.0" startEvent="default" zOrder="200">
      <property name="text" value=""/>
      <property name="requires" value="intro"/>
    </actor>
    <actor costume="portcullis" x="120" y="-60" direction="0.0" heading="0.0" startEvent="default" zOrder="201">
      <property name="text" value=""/>
      <property name="requires" value="intro"/>
    </actor>
    <actor costume="portcullis" x="0" y="-180" direction="0.0" heading="0.0" startEvent="default" zOrder="202">
      <property name="text" value="Rocks(3) and Balloons(3)"/>
      <property name="requires" value="rocks3,balloons3"/>
    </actor>
    <actor costume="portcullis" x="-120" y="60" direction="0.0" heading="0.0" startEvent="default" zOrder="203">
      <property name="text" value="Grenades(3) and Balloons(3)"/>
      <property name="requires" value="grenades3,balloons3"/>
    </actor>
    <actor costume="portcullis" x="120" y="60" direction="0.0" heading="0.0" startEvent="default" zOrder="204">
      <property name="text" value="Rocks(3)"/>
      <property name="requires" value="rocks3"/>
    </actor>
    <actor costume="wall" x="180" y="0" direction="0.0" heading="0.0" startEvent="default" zOrder="205"/>
    <actor costume="wall" x="-180" y="0" direction="0.0" heading="0.0" startEvent="default" zOrder="206"/>
    <actor costume="wall" x="-240" y="240" direction="0.0" heading="0.0" startEvent="default" zOrder="207"/>
    <actor costume="wallNW" x="180" y="-240" direction="0.0" heading="0.0" startEvent="default" zOrder="208"/>
    <actor costume="wall" x="180" y="-300" direction="0.0" heading="0.0" startEvent="default" zOrder="209"/>
    <actor costume="wall" x="240" y="-240" direction="0.0" heading="0.0" startEvent="default" zOrder="210"/>
    <actor costume="wallNE" x="-180" y="-240" direction="0.0" heading="0.0" startEvent="default" zOrder="211"/>
    <actor costume="wall" x="-180" y="-300" direction="0.0" heading="0.0" startEvent="default" zOrder="212"/>
    <actor costume="wall" x="-240" y="-240" direction="0.0" heading="0.0" startEvent="default" zOrder="213"/>
    <actor costume="wall" x="240" y="0" direction="0.0" heading="0.0" startEvent="default" zOrder="214"/>
    <actor costume="wall" x="300" y="0" direction="0.0" heading="0.0" startEvent="default" zOrder="215"/>
    <actor costume="wall" x="360" y="0" direction="0.0" heading="0.0" startEvent="default" zOrder="216"/>
    <actor costume="wall" x="-240" y="0" direction="0.0" heading="0.0" startEvent="default" zOrder="217"/>
    <actor costume="wall" x="-360" y="0" direction="0.0" heading="0.0" startEvent="default" zOrder="218"/>
    <actor costume="wall" x="-300" y="0" direction="0.0" heading="0.0" startEvent="default" zOrder="219"/>
    <actor costume="wall" x="300" y="-240" direction="0.0" heading="0.0" startEvent="default" zOrder="220"/>
    <actor costume="wall" x="360" y="-60" direction="0.0" heading="0.0" startEvent="default" zOrder="221"/>
    <actor costume="wall" x="420" y="-300" direction="0.0" heading="0.0" startEvent="default" zOrder="222"/>
    <actor costume="wall" x="360" y="-120" direction="0.0" heading="0.0" startEvent="default" zOrder="223"/>
    <actor costume="wall" x="360" y="-240" direction="0.0" heading="0.0" startEvent="default" zOrder="224"/>
    <actor costume="wall" x="420" y="-60" direction="0.0" heading="0.0" startEvent="default" zOrder="225"/>
    <text text="Combined" font="Boycott" size="22" color="#ffffff" xAlignment="0.5" yAlignment="0.5" x="0" y="-300" direction="0.0" heading="0.0" startEvent="default" zOrder="226">
      <makeup classname="uk.co.nickthecoder.itchy.makeup.Shadow">
        <property name="dx" value="2"/>
        <property name="dy" value="-1"/>
        <property name="color" value="#000000ff"/>
      </makeup>
    </text>
    <actor costume="wall" x="-300" y="-240" direction="0.0" heading="0.0" startEvent="default" zOrder="227"/>
    <actor costume="wall" x="-360" y="-240" direction="0.0" heading="0.0" startEvent="default" zOrder="228"/>
    <actor costume="wall" x="-360" y="-120" direction="0.0" heading="0.0" startEvent="default" zOrder="230"/>
    <actor costume="wall" x="-360" y="-60" direction="0.0" heading="0.0" startEvent="default" zOrder="231"/>
    <actor costume="wall" x="480" y="-60" direction="0.0" heading="0.0" startEvent="default" zOrder="232"/>
    <text text="Balloons" font="Boycott" size="22" color="#ffffff" xAlignment="0.5" yAlignment="0.5" x="-240" y="-120" direction="0.0" heading="0.0" startEvent="default" zOrder="233">
      <makeup classname="uk.co.nickthecoder.itchy.makeup.Shadow">
        <property name="dx" value="2"/>
        <property name="dy" value="-1"/>
        <property name="color" value="#000000ff"/>
      </makeup>
    </text>
    <text text="Grenades" font="Boycott" size="22" color="#ffffff" xAlignment="0.5" yAlignment="0.5" x="240" y="120" direction="0.0" heading="0.0" startEvent="default" zOrder="234">
      <makeup classname="uk.co.nickthecoder.itchy.makeup.Shadow">
        <property name="dx" value="2"/>
        <property name="dy" value="-1"/>
        <property name="color" value="#000000ff"/>
      </makeup>
    </text>
    <actor costume="warp" x="240" y="-120" direction="0.0" heading="0.0" startEvent="default" zOrder="236">
      <property name="exitX" value="0"/>
      <property name="exitY" value="-1"/>
      <property name="scene" value="rocks"/>
    </actor>
    <text text="Rocks" font="Boycott" size="22" color="#ffffff" xAlignment="0.5" yAlignment="0.5" x="240" y="-120" direction="0.0" heading="0.0" startEvent="default" zOrder="237">
      <makeup classname="uk.co.nickthecoder.itchy.makeup.Shadow">
        <property name="dx" value="2"/>
        <property name="dy" value="-1"/>
        <property name="color" value="#000000ff"/>
      </makeup>
    </text>
    <actor costume="portcullis" x="0" y="180" direction="0.0" heading="0.0" startEvent="default" zOrder="239">
      <property name="text" value="Grenades(3) and Balloons(3)"/>
      <property name="requires" value="grenades3,balloon3"/>
    </actor>
    <actor costume="warp" x="-240" y="120" direction="0.0" heading="0.0" startEvent="default" zOrder="240">
      <property name="exitX" value="0"/>
      <property name="exitY" value="1"/>
      <property name="scene" value="cars"/>
    </actor>
    <actor costume="wallSE" x="-180" y="240" direction="0.0" heading="0.0" startEvent="default" zOrder="242"/>
    <actor costume="wallSW" x="180" y="240" direction="0.0" heading="0.0" startEvent="default" zOrder="243"/>
    <actor costume="wall" x="300" y="240" direction="0.0" heading="0.0" startEvent="default" zOrder="244"/>
    <actor costume="wall" x="360" y="120" direction="0.0" heading="0.0" startEvent="default" zOrder="246"/>
    <actor costume="wall" x="360" y="240" direction="0.0" heading="0.0" startEvent="default" zOrder="247"/>
    <actor costume="wall" x="660" y="360" direction="0.0" heading="0.0" startEvent="default" zOrder="248"/>
    <actor costume="wall" x="360" y="60" direction="0.0" heading="0.0" startEvent="default" zOrder="249"/>
    <actor costume="wall" x="-300" y="240" direction="0.0" heading="0.0" startEvent="default" zOrder="250"/>
    <actor costume="wall" x="-360" y="240" direction="0.0" heading="0.0" startEvent="default" zOrder="251"/>
    <actor costume="wall" x="-360" y="180" direction="0.0" heading="0.0" startEvent="default" zOrder="252"/>
    <actor costume="wall" x="-360" y="120" direction="0.0" heading="0.0" startEvent="default" zOrder="253"/>
    <actor costume="wall" x="-360" y="60" direction="0.0" heading="0.0" startEvent="default" zOrder="254"/>
    <actor costume="wall" x="-180" y="300" direction="0.0" heading="0.0" startEvent="default" zOrder="256"/>
    <actor costume="wall" x="180" y="300" direction="0.0" heading="0.0" startEvent="default" zOrder="257"/>
    <actor costume="warp" x="0" y="300" direction="0.0" heading="0.0" startEvent="default" zOrder="259">
      <property name="exitX" value="0"/>
      <property name="exitY" value="1"/>
      <property name="scene" value="furniture"/>
    </actor>
    <text text="Cars" font="Boycott" size="22" color="#ffffff" xAlignment="0.5" yAlignment="0.5" x="-240" y="120" direction="0.0" heading="0.0" startEvent="default" zOrder="260">
      <makeup classname="uk.co.nickthecoder.itchy.makeup.Shadow">
        <property name="dx" value="2"/>
        <property name="dy" value="-1"/>
        <property name="color" value="#000000ff"/>
      </makeup>
    </text>
    <text text="Furniture" font="Boycott" size="22" color="#ffffff" xAlignment="0.5" yAlignment="0.5" x="0" y="300" direction="0.0" heading="0.0" startEvent="default" zOrder="261">
      <makeup classname="uk.co.nickthecoder.itchy.makeup.Shadow">
        <property name="dx" value="2"/>
        <property name="dy" value="-1"/>
        <property name="color" value="#000000ff"/>
      </makeup>
    </text>
    <actor costume="wall" x="-120" y="-420" direction="0.0" heading="0.0" startEvent="default" zOrder="262"/>
    <actor costume="wall" x="-180" y="-360" direction="0.0" heading="0.0" startEvent="default" zOrder="263"/>
    <actor costume="wall" x="-60" y="-420" direction="0.0" heading="0.0" startEvent="default" zOrder="264"/>
    <actor costume="wall" x="0" y="-420" direction="0.0" heading="0.0" startEvent="default" zOrder="265"/>
    <actor costume="wall" x="60" y="-420" direction="0.0" heading="0.0" startEvent="default" zOrder="266"/>
    <actor costume="wall" x="120" y="-420" direction="0.0" heading="0.0" startEvent="default" zOrder="267"/>
    <actor costume="wall" x="180" y="-360" direction="0.0" heading="0.0" startEvent="default" zOrder="268"/>
    <actor costume="wallSE" x="180" y="-420" direction="0.0" heading="0.0" startEvent="default" zOrder="269"/>
    <actor costume="wallSW" x="-180" y="-420" direction="0.0" heading="0.0" startEvent="default" zOrder="270"/>
    <actor costume="portcullis" x="360" y="-180" direction="0.0" heading="0.0" startEvent="default" zOrder="271">
      <property name="text" value="Rocks"/>
      <property name="requires" value="rocks"/>
    </actor>
    <actor costume="wall" x="600" y="-300" direction="0.0" heading="0.0" startEvent="default" zOrder="272"/>
    <actor costume="wall" x="540" y="-300" direction="0.0" heading="0.0" startEvent="default" zOrder="273"/>
    <actor costume="wall" x="600" y="-120" direction="0.0" heading="0.0" startEvent="default" zOrder="274"/>
    <actor costume="wall" x="600" y="-180" direction="0.0" heading="0.0" startEvent="default" zOrder="275"/>
    <actor costume="wall" x="660" y="-360" direction="0.0" heading="0.0" startEvent="default" zOrder="276"/>
    <actor costume="wall" x="660" y="-120" direction="0.0" heading="0.0" startEvent="default" zOrder="277"/>
    <actor costume="wall" x="540" y="-60" direction="0.0" heading="0.0" startEvent="default" zOrder="279"/>
    <actor costume="warp" x="480" y="-180" direction="0.0" heading="0.0" startEvent="default" zOrder="280">
      <property name="exitX" value="0"/>
      <property name="exitY" value="-1"/>
      <property name="scene" value="rocks2"/>
    </actor>
    <actor costume="wall" x="720" y="-120" direction="0.0" heading="0.0" startEvent="default" zOrder="281"/>
    <actor costume="wall" x="780" y="360" direction="0.0" heading="0.0" startEvent="default" zOrder="282"/>
    <actor costume="wall" x="900" y="-180" direction="0.0" heading="0.0" startEvent="default" zOrder="283"/>
    <actor costume="wall" x="840" y="-180" direction="0.0" heading="0.0" startEvent="default" zOrder="285"/>
    <actor costume="wall" x="840" y="-240" direction="0.0" heading="0.0" startEvent="default" zOrder="286"/>
    <actor costume="wall" x="780" y="-360" direction="0.0" heading="0.0" startEvent="default" zOrder="287"/>
    <actor costume="warp" x="720" y="-240" direction="0.0" heading="0.0" startEvent="default" zOrder="288">
      <property name="exitX" value="0"/>
      <property name="exitY" value="-1"/>
      <property name="scene" value="rocks3"/>
    </actor>
    <actor costume="portcullis" x="840" y="-300" direction="0.0" heading="0.0" startEvent="default" zOrder="289">
      <property name="text" value="Rocks(3)"/>
      <property name="requires" value="rocks3"/>
    </actor>
    <actor costume="portcullis" x="360" y="180" direction="0.0" heading="0.0" startEvent="default" zOrder="290">
      <property name="text" value="Grenades"/>
      <property name="requires" value="grenades"/>
    </actor>
    <actor costume="portcullis" x="600" y="240" direction="0.0" heading="0.0" startEvent="default" zOrder="291">
      <property name="text" value="Grenades(2)"/>
      <property name="requires" value="grenades2"/>
    </actor>
    <actor costume="warp" x="480" y="180" direction="0.0" heading="0.0" startEvent="default" zOrder="292">
      <property name="exitX" value="0"/>
      <property name="exitY" value="-1"/>
      <property name="scene" value="grenades2"/>
    </actor>
    <actor costume="warp" x="720" y="240" direction="0.0" heading="0.0" startEvent="default" zOrder="293">
      <property name="exitX" value="0"/>
      <property name="exitY" value="-1"/>
      <property name="scene" value="grenades3"/>
    </actor>
    <actor costume="portcullis" x="840" y="300" direction="0.0" heading="0.0" startEvent="default" zOrder="295">
      <property name="text" value="Grenades(3)"/>
      <property name="requires" value="grenades3"/>
    </actor>
    <actor costume="wall" x="480" y="-300" direction="0.0" heading="0.0" startEvent="default" zOrder="297"/>
    <actor costume="wall" x="720" y="-360" direction="0.0" heading="0.0" startEvent="default" zOrder="298"/>
    <actor costume="player" id="player" x="0" y="120" direction="0.0" heading="0.0" startEvent="default" zOrder="300"/>
    <actor costume="wall" x="420" y="60" direction="0.0" heading="0.0" startEvent="default" zOrder="305"/>
    <actor costume="wall" x="480" y="60" direction="0.0" heading="0.0" startEvent="default" zOrder="306"/>
    <actor costume="wall" x="540" y="60" direction="0.0" heading="0.0" startEvent="default" zOrder="307"/>
    <actor costume="wall" x="420" y="300" direction="0.0" heading="0.0" startEvent="default" zOrder="309"/>
    <actor costume="wall" x="600" y="300" direction="0.0" heading="0.0" startEvent="default" zOrder="310"/>
    <actor costume="wall" x="660" y="120" direction="0.0" heading="0.0" startEvent="default" zOrder="311"/>
    <actor costume="wall" x="720" y="120" direction="0.0" heading="0.0" startEvent="default" zOrder="312"/>
    <actor costume="wall" x="780" y="120" direction="0.0" heading="0.0" startEvent="default" zOrder="313"/>
    <actor costume="wall" x="840" y="180" direction="0.0" heading="0.0" startEvent="default" zOrder="314"/>
    <actor costume="wall" x="600" y="120" direction="0.0" heading="0.0" startEvent="default" zOrder="315"/>
    <actor costume="wall" x="960" y="-180" direction="0.0" heading="0.0" startEvent="default" zOrder="316"/>
    <actor costume="wall" x="780" y="-120" direction="0.0" heading="0.0" startEvent="default" zOrder="317"/>
    <actor costume="portcullis" x="600" y="-240" direction="0.0" heading="0.0" startEvent="default" zOrder="318">
      <property name="text" value="Rocks(2)"/>
      <property name="requires" value="rocks2"/>
    </actor>
    <actor costume="wallSE" x="600" y="60" direction="0.0" heading="0.0" startEvent="default" zOrder="319"/>
    <actor costume="wallSE" x="840" y="120" direction="0.0" heading="0.0" startEvent="default" zOrder="320"/>
    <actor costume="wallNE" x="600" y="-60" direction="0.0" heading="0.0" startEvent="default" zOrder="321"/>
    <actor costume="wallNE" x="840" y="-120" direction="0.0" heading="0.0" startEvent="default" zOrder="322"/>
    <actor costume="wallSW" x="600" y="-360" direction="0.0" heading="0.0" startEvent="default" zOrder="324"/>
    <actor costume="wallSW" x="360" y="-300" direction="0.0" heading="0.0" startEvent="default" zOrder="326"/>
    <actor costume="wallNW" x="600" y="360" direction="0.0" heading="0.0" startEvent="default" zOrder="328"/>
    <actor costume="wallNW" x="360" y="300" direction="0.0" heading="0.0" startEvent="default" zOrder="329"/>
    <actor costume="wall" x="1020" y="-180" direction="0.0" heading="0.0" startEvent="default" zOrder="330"/>
    <actor costume="wall" x="840" y="-360" direction="0.0" heading="0.0" startEvent="default" zOrder="331"/>
    <actor costume="wall" x="900" y="-420" direction="0.0" heading="0.0" startEvent="default" zOrder="333"/>
    <actor costume="wall" x="960" y="-420" direction="0.0" heading="0.0" startEvent="default" zOrder="334"/>
    <actor costume="wall" x="1020" y="-420" direction="0.0" heading="0.0" startEvent="default" zOrder="335"/>
    <actor costume="wall" x="1080" y="-240" direction="0.0" heading="0.0" startEvent="default" zOrder="337"/>
    <actor costume="wall" x="1080" y="-300" direction="0.0" heading="0.0" startEvent="default" zOrder="338"/>
    <actor costume="wall" x="1080" y="-420" direction="0.0" heading="0.0" startEvent="default" zOrder="340"/>
    <actor costume="wall" x="1140" y="-240" direction="0.0" heading="0.0" startEvent="default" zOrder="341"/>
    <actor costume="wall" x="1680" y="-240" direction="0.0" heading="0.0" startEvent="default" zOrder="342"/>
    <actor costume="wall" x="1260" y="-240" direction="0.0" heading="0.0" startEvent="default" zOrder="343"/>
    <actor costume="wall" x="1320" y="-300" direction="0.0" heading="0.0" startEvent="default" zOrder="345"/>
    <actor costume="wall" x="1320" y="-360" direction="0.0" heading="0.0" startEvent="default" zOrder="346"/>
    <actor costume="wall" x="1140" y="-480" direction="0.0" heading="0.0" startEvent="default" zOrder="349"/>
    <actor costume="wall" x="1200" y="-480" direction="0.0" heading="0.0" startEvent="default" zOrder="350"/>
    <actor costume="wall" x="1260" y="-480" direction="0.0" heading="0.0" startEvent="default" zOrder="351"/>
    <actor costume="wall" x="1320" y="-480" direction="0.0" heading="0.0" startEvent="default" zOrder="352"/>
    <actor costume="wall" x="1380" y="-540" direction="0.0" heading="0.0" startEvent="default" zOrder="354"/>
    <actor costume="wall" x="1380" y="-300" direction="0.0" heading="0.0" startEvent="default" zOrder="355"/>
    <actor costume="wall" x="1440" y="-300" direction="0.0" heading="0.0" startEvent="default" zOrder="357"/>
    <actor costume="wall" x="1560" y="-360" direction="0.0" heading="0.0" startEvent="default" zOrder="359"/>
    <actor costume="wall" x="1560" y="-420" direction="0.0" heading="0.0" startEvent="default" zOrder="360"/>
    <actor costume="wall" x="1560" y="-480" direction="0.0" heading="0.0" startEvent="default" zOrder="361"/>
    <actor costume="wall" x="1500" y="-540" direction="0.0" heading="0.0" startEvent="default" zOrder="364"/>
    <actor costume="wall" x="1440" y="-540" direction="0.0" heading="0.0" startEvent="default" zOrder="366"/>
    <actor costume="wallSW" x="840" y="-420" direction="0.0" heading="0.0" startEvent="default" zOrder="369"/>
    <actor costume="wallSW" x="1080" y="-480" direction="0.0" heading="0.0" startEvent="default" zOrder="370"/>
    <actor costume="wallSW" x="1320" y="-540" direction="0.0" heading="0.0" startEvent="default" zOrder="371"/>
    <actor costume="wallSE" x="1560" y="-540" direction="0.0" heading="0.0" startEvent="default" zOrder="372"/>
    <actor costume="wallNE" x="1080" y="-180" direction="0.0" heading="0.0" startEvent="default" zOrder="373"/>
    <actor costume="portcullis" x="1080" y="-360" direction="0.0" heading="0.0" startEvent="default" zOrder="374">
      <property name="text" value="Rocks(4)"/>
      <property name="requires" value="rocks4"/>
    </actor>
    <actor costume="portcullis" x="1320" y="-420" direction="0.0" heading="0.0" startEvent="default" zOrder="375">
      <property name="text" value="Rocks(5)"/>
      <property name="requires" value="rocks5"/>
    </actor>
    <actor costume="warp" x="960" y="-300" direction="0.0" heading="0.0" startEvent="default" zOrder="376">
      <property name="exitX" value="0"/>
      <property name="exitY" value="-1"/>
      <property name="scene" value="rocks4"/>
    </actor>
    <actor costume="warp" x="1200" y="-360" direction="0.0" heading="0.0" startEvent="default" zOrder="377">
      <property name="exitX" value="0"/>
      <property name="exitY" value="-1"/>
      <property name="scene" value="rocks5"/>
    </actor>
    <actor costume="warp" x="1440" y="-420" direction="0.0" heading="0.0" startEvent="default" zOrder="378">
      <property name="exitX" value="0"/>
      <property name="exitY" value="-1"/>
      <property name="scene" value="rocks6"/>
    </actor>
    <actor costume="wall" x="900" y="180" direction="0.0" heading="0.0" startEvent="default" zOrder="379"/>
    <actor costume="wall" x="960" y="180" direction="0.0" heading="0.0" startEvent="default" zOrder="380"/>
    <actor costume="wall" x="1020" y="180" direction="0.0" heading="0.0" startEvent="default" zOrder="381"/>
    <actor costume="wall" x="1080" y="240" direction="0.0" heading="0.0" startEvent="default" zOrder="383"/>
    <actor costume="wall" x="1080" y="300" direction="0.0" heading="0.0" startEvent="default" zOrder="384"/>
    <actor costume="wall" x="1080" y="420" direction="0.0" heading="0.0" startEvent="default" zOrder="386"/>
    <actor costume="wall" x="840" y="360" direction="0.0" heading="0.0" startEvent="default" zOrder="388"/>
    <actor costume="wall" x="900" y="420" direction="0.0" heading="0.0" startEvent="default" zOrder="389"/>
    <actor costume="wall" x="960" y="420" direction="0.0" heading="0.0" startEvent="default" zOrder="390"/>
    <actor costume="wall" x="1020" y="420" direction="0.0" heading="0.0" startEvent="default" zOrder="391"/>
    <actor costume="wall" x="1140" y="240" direction="0.0" heading="0.0" startEvent="default" zOrder="392"/>
    <actor costume="wall" x="1200" y="240" direction="0.0" heading="0.0" startEvent="default" zOrder="393"/>
    <actor costume="wall" x="1260" y="240" direction="0.0" heading="0.0" startEvent="default" zOrder="394"/>
    <actor costume="wall" x="1320" y="300" direction="0.0" heading="0.0" startEvent="default" zOrder="397"/>
    <actor costume="wall" x="1320" y="360" direction="0.0" heading="0.0" startEvent="default" zOrder="398"/>
    <actor costume="wall" x="1140" y="480" direction="0.0" heading="0.0" startEvent="default" zOrder="401"/>
    <actor costume="wall" x="1260" y="480" direction="0.0" heading="0.0" startEvent="default" zOrder="402"/>
    <actor costume="wall" x="1320" y="480" direction="0.0" heading="0.0" startEvent="default" zOrder="403"/>
    <actor costume="wall" x="1200" y="480" direction="0.0" heading="0.0" startEvent="default" zOrder="404"/>
    <actor costume="wall" x="1380" y="300" direction="0.0" heading="0.0" startEvent="default" zOrder="405"/>
    <actor costume="wall" x="1500" y="300" direction="0.0" heading="0.0" startEvent="default" zOrder="407"/>
    <actor costume="wall" x="1560" y="360" direction="0.0" heading="0.0" startEvent="default" zOrder="409"/>
    <actor costume="wall" x="1560" y="420" direction="0.0" heading="0.0" startEvent="default" zOrder="410"/>
    <actor costume="wall" x="1560" y="480" direction="0.0" heading="0.0" startEvent="default" zOrder="411"/>
    <actor costume="wall" x="1500" y="540" direction="0.0" heading="0.0" startEvent="default" zOrder="413"/>
    <actor costume="wall" x="1440" y="540" direction="0.0" heading="0.0" startEvent="default" zOrder="414"/>
    <actor costume="wall" x="1380" y="540" direction="0.0" heading="0.0" startEvent="default" zOrder="416"/>
    <actor costume="wallNW" x="1320" y="540" direction="0.0" heading="0.0" startEvent="default" zOrder="418"/>
    <actor costume="wallNW" x="1080" y="480" direction="0.0" heading="0.0" startEvent="default" zOrder="419"/>
    <actor costume="wallSE" x="1560" y="300" direction="0.0" heading="0.0" startEvent="default" zOrder="420"/>
    <actor costume="wallSE" x="1320" y="240" direction="0.0" heading="0.0" startEvent="default" zOrder="421"/>
    <actor costume="wallSE" x="1080" y="180" direction="0.0" heading="0.0" startEvent="default" zOrder="422"/>
    <actor costume="wallNW" x="840" y="420" direction="0.0" heading="0.0" startEvent="default" zOrder="423"/>
    <actor costume="portcullis" x="1080" y="360" direction="0.0" heading="0.0" startEvent="default" zOrder="424">
      <property name="text" value="Grenades(4)"/>
      <property name="requires" value="grenades4"/>
    </actor>
    <actor costume="portcullis" x="1320" y="420" direction="0.0" heading="0.0" startEvent="default" zOrder="425">
      <property name="text" value="Grenades(5)"/>
      <property name="requires" value="grenades5"/>
    </actor>
    <actor costume="wallNE" x="1560" y="540" direction="0.0" heading="0.0" startEvent="default" zOrder="426"/>
    <actor costume="warp" x="960" y="300" direction="0.0" heading="0.0" startEvent="default" zOrder="427">
      <property name="exitX" value="0"/>
      <property name="exitY" value="-1"/>
      <property name="scene" value="grenades4"/>
    </actor>
    <actor costume="warp" x="1200" y="360" direction="0.0" heading="0.0" startEvent="default" zOrder="428">
      <property name="exitX" value="0"/>
      <property name="exitY" value="-1"/>
      <property name="scene" value="grenades5"/>
    </actor>
    <actor costume="warp" x="1440" y="420" direction="0.0" heading="0.0" startEvent="default" zOrder="429">
      <property name="exitX" value="0"/>
      <property name="exitY" value="-1"/>
      <property name="scene" value="grenades6"/>
    </actor>
    <actor costume="portcullis" x="1500" y="-300" direction="0.0" heading="0.0" startEvent="default" zOrder="430">
      <property name="text" value="Rocks(6)"/>
      <property name="requires" value="rocks6"/>
    </actor>
    <actor costume="portcullis" x="1440" y="300" direction="0.0" heading="0.0" startEvent="default" zOrder="431">
      <property name="text" value="Grenades(6)"/>
      <property name="requires" value="grenades6"/>
    </actor>
    <actor costume="wallNE" x="1740" y="360" direction="0.0" heading="0.0" startEvent="default" zOrder="432"/>
    <actor costume="wall" x="1620" y="360" direction="0.0" heading="0.0" startEvent="default" zOrder="433"/>
    <actor costume="wall" x="1680" y="360" direction="0.0" heading="0.0" startEvent="default" zOrder="434"/>
    <actor costume="wall" x="1740" y="300" direction="0.0" heading="0.0" startEvent="default" zOrder="435"/>
    <actor costume="wall" x="1740" y="240" direction="0.0" heading="0.0" startEvent="default" zOrder="436"/>
    <actor costume="wall" x="1740" y="180" direction="0.0" heading="0.0" startEvent="default" zOrder="437"/>
    <actor costume="wall" x="1680" y="-180" direction="0.0" heading="0.0" startEvent="default" zOrder="440"/>
    <actor costume="wall" x="1560" y="-300" direction="0.0" heading="0.0" startEvent="default" zOrder="442"/>
    <actor costume="wallSE" x="1680" y="-300" direction="0.0" heading="0.0" startEvent="default" zOrder="445"/>
    <actor costume="wall" x="1440" y="-240" direction="0.0" heading="0.0" startEvent="default" zOrder="447"/>
    <actor costume="wall" x="1500" y="-60" direction="0.0" heading="0.0" startEvent="default" zOrder="448"/>
    <actor costume="wall" x="1620" y="-60" direction="0.0" heading="0.0" startEvent="default" zOrder="450"/>
    <actor costume="wall" x="1620" y="-300" direction="0.0" heading="0.0" startEvent="default" zOrder="452"/>
    <actor costume="wall" x="1440" y="-120" direction="0.0" heading="0.0" startEvent="default" zOrder="454"/>
    <actor costume="wall" x="1440" y="-180" direction="0.0" heading="0.0" startEvent="default" zOrder="455"/>
    <actor costume="wallNW" x="1440" y="-60" direction="0.0" heading="0.0" startEvent="default" zOrder="460"/>
    <actor costume="wallNE" x="1680" y="-60" direction="0.0" heading="0.0" startEvent="default" zOrder="461"/>
    <actor costume="warp" x="1560" y="-180" direction="0.0" heading="0.0" startEvent="default" zOrder="462">
      <property name="exitX" value="0"/>
      <property name="exitY" value="-1"/>
      <property name="scene" value="rocks7"/>
    </actor>
    <actor costume="portcullis" x="1560" y="-60" direction="0.0" heading="0.0" startEvent="default" zOrder="463">
      <property name="text" value="Rocks(7)"/>
      <property name="requires" value="rocks7"/>
    </actor>
    <text text="2" font="Boycott" size="22" color="#ffffff" xAlignment="0.5" yAlignment="0.5" x="480" y="-180" direction="0.0" heading="0.0" startEvent="default" zOrder="464">
      <makeup classname="uk.co.nickthecoder.itchy.makeup.Shadow">
        <property name="dx" value="2"/>
        <property name="dy" value="-1"/>
        <property name="color" value="#000000ff"/>
      </makeup>
    </text>
    <text text="3" font="Boycott" size="22" color="#ffffff" xAlignment="0.5" yAlignment="0.5" x="720" y="-240" direction="0.0" heading="0.0" startEvent="default" zOrder="465">
      <makeup classname="uk.co.nickthecoder.itchy.makeup.Shadow">
        <property name="dx" value="2"/>
        <property name="dy" value="-1"/>
        <property name="color" value="#000000ff"/>
      </makeup>
    </text>
    <text text="4" font="Boycott" size="22" color="#ffffff" xAlignment="0.5" yAlignment="0.5" x="960" y="-300" direction="0.0" heading="0.0" startEvent="default" zOrder="466">
      <makeup classname="uk.co.nickthecoder.itchy.makeup.Shadow">
        <property name="dx" value="2"/>
        <property name="dy" value="-1"/>
        <property name="color" value="#000000ff"/>
      </makeup>
    </text>
    <text text="5" font="Boycott" size="22" color="#ffffff" xAlignment="0.5" yAlignment="0.5" x="1200" y="-360" direction="0.0" heading="0.0" startEvent="default" zOrder="467">
      <makeup classname="uk.co.nickthecoder.itchy.makeup.Shadow">
        <property name="dx" value="2"/>
        <property name="dy" value="-1"/>
        <property name="color" value="#000000ff"/>
      </makeup>
    </text>
    <text text="6" font="Boycott" size="22" color="#ffffff" xAlignment="0.5" yAlignment="0.5" x="1440" y="-420" direction="0.0" heading="0.0" startEvent="default" zOrder="468">
      <makeup classname="uk.co.nickthecoder.itchy.makeup.Shadow">
        <property name="dx" value="2"/>
        <property name="dy" value="-1"/>
        <property name="color" value="#000000ff"/>
      </makeup>
    </text>
    <text text="7" font="Boycott" size="22" color="#ffffff" xAlignment="0.5" yAlignment="0.5" x="1560" y="-180" direction="0.0" heading="0.0" startEvent="default" zOrder="469">
      <makeup classname="uk.co.nickthecoder.itchy.makeup.Shadow">
        <property name="dx" value="2"/>
        <property name="dy" value="-1"/>
        <property name="color" value="#000000ff"/>
      </makeup>
    </text>
    <text text="2" font="Boycott" size="22" color="#ffffff" xAlignment="0.5" yAlignment="0.5" x="480" y="180" direction="0.0" heading="0.0" startEvent="default" zOrder="470">
      <makeup classname="uk.co.nickthecoder.itchy.makeup.Shadow">
        <property name="dx" value="2"/>
        <property name="dy" value="-1"/>
        <property name="color" value="#000000ff"/>
      </makeup>
    </text>
    <text text="3" font="Boycott" size="22" color="#ffffff" xAlignment="0.5" yAlignment="0.5" x="720" y="240" direction="0.0" heading="0.0" startEvent="default" zOrder="471">
      <makeup classname="uk.co.nickthecoder.itchy.makeup.Shadow">
        <property name="dx" value="2"/>
        <property name="dy" value="-1"/>
        <property name="color" value="#000000ff"/>
      </makeup>
    </text>
    <text text="4" font="Boycott" size="22" color="#ffffff" xAlignment="0.5" yAlignment="0.5" x="960" y="300" direction="0.0" heading="0.0" startEvent="default" zOrder="472">
      <makeup classname="uk.co.nickthecoder.itchy.makeup.Shadow">
        <property name="dx" value="2"/>
        <property name="dy" value="-1"/>
        <property name="color" value="#000000ff"/>
      </makeup>
    </text>
    <text text="5" font="Boycott" size="22" color="#ffffff" xAlignment="0.5" yAlignment="0.5" x="1200" y="360" direction="0.0" heading="0.0" startEvent="default" zOrder="473">
      <makeup classname="uk.co.nickthecoder.itchy.makeup.Shadow">
        <property name="dx" value="2"/>
        <property name="dy" value="-1"/>
        <property name="color" value="#000000ff"/>
      </makeup>
    </text>
    <text text="6" font="Boycott" size="22" color="#ffffff" xAlignment="0.5" yAlignment="0.5" x="1440" y="420" direction="0.0" heading="0.0" startEvent="default" zOrder="474">
      <makeup classname="uk.co.nickthecoder.itchy.makeup.Shadow">
        <property name="dx" value="2"/>
        <property name="dy" value="-1"/>
        <property name="color" value="#000000ff"/>
      </makeup>
    </text>
    <actor costume="wall" x="1740" y="120" direction="0.0" heading="0.0" startEvent="default" zOrder="475"/>
    <actor costume="wall" x="1740" y="60" direction="0.0" heading="0.0" startEvent="default" zOrder="476"/>
    <actor costume="wall" x="1740" y="0" direction="0.0" heading="0.0" startEvent="default" zOrder="477"/>
    <actor costume="wall" x="1740" y="-60" direction="0.0" heading="0.0" startEvent="default" zOrder="478"/>
    <actor costume="wall" x="1680" y="-120" direction="0.0" heading="0.0" startEvent="default" zOrder="479"/>
    <actor costume="wallSE" x="1740" y="-120" direction="0.0" heading="0.0" startEvent="default" zOrder="480"/>
    <actor costume="wall" x="1200" y="-240" direction="0.0" heading="0.0" startEvent="default" zOrder="481"/>
    <actor costume="wallNE" x="1320" y="-240" direction="0.0" heading="0.0" startEvent="default" zOrder="482"/>
    <actor costume="wall" x="-420" y="-60" direction="0.0" heading="0.0" startEvent="default" zOrder="483"/>
    <actor costume="wall" x="-480" y="-60" direction="0.0" heading="0.0" startEvent="default" zOrder="484"/>
    <actor costume="wall" x="-540" y="-60" direction="0.0" heading="0.0" startEvent="default" zOrder="485"/>
    <actor costume="wall" x="-600" y="-120" direction="0.0" heading="0.0" startEvent="default" zOrder="487"/>
    <actor costume="wall" x="-600" y="-180" direction="0.0" heading="0.0" startEvent="default" zOrder="488"/>
    <actor costume="wall" x="-600" y="-300" direction="0.0" heading="0.0" startEvent="default" zOrder="490"/>
    <actor costume="wall" x="-540" y="-300" direction="0.0" heading="0.0" startEvent="default" zOrder="491"/>
    <actor costume="wall" x="-480" y="-300" direction="0.0" heading="0.0" startEvent="default" zOrder="492"/>
    <actor costume="wall" x="-420" y="-300" direction="0.0" heading="0.0" startEvent="default" zOrder="493"/>
    <actor costume="wall" x="-660" y="-120" direction="0.0" heading="0.0" startEvent="default" zOrder="495"/>
    <actor costume="wall" x="-780" y="-120" direction="0.0" heading="0.0" startEvent="default" zOrder="496"/>
    <actor costume="wall" x="-720" y="-120" direction="0.0" heading="0.0" startEvent="default" zOrder="497"/>
    <actor costume="wall" x="-840" y="-180" direction="0.0" heading="0.0" startEvent="default" zOrder="499"/>
    <actor costume="wall" x="-840" y="-240" direction="0.0" heading="0.0" startEvent="default" zOrder="500"/>
    <actor costume="wall" x="-840" y="-360" direction="0.0" heading="0.0" startEvent="default" zOrder="502"/>
    <actor costume="wall" x="-780" y="-360" direction="0.0" heading="0.0" startEvent="default" zOrder="503"/>
    <actor costume="wall" x="-720" y="-360" direction="0.0" heading="0.0" startEvent="default" zOrder="504"/>
    <actor costume="wall" x="-660" y="-360" direction="0.0" heading="0.0" startEvent="default" zOrder="505"/>
    <actor costume="wall" x="-900" y="-180" direction="0.0" heading="0.0" startEvent="default" zOrder="507"/>
    <actor costume="wall" x="-960" y="-180" direction="0.0" heading="0.0" startEvent="default" zOrder="508"/>
    <actor costume="wall" x="-1020" y="-180" direction="0.0" heading="0.0" startEvent="default" zOrder="509"/>
    <actor costume="wall" x="-1080" y="-240" direction="0.0" heading="0.0" startEvent="default" zOrder="511"/>
    <actor costume="wall" x="-1080" y="-300" direction="0.0" heading="0.0" startEvent="default" zOrder="512"/>
    <actor costume="wall" x="-1080" y="-420" direction="0.0" heading="0.0" startEvent="default" zOrder="514"/>
    <actor costume="wall" x="-1020" y="-420" direction="0.0" heading="0.0" startEvent="default" zOrder="515"/>
    <actor costume="wall" x="-960" y="-420" direction="0.0" heading="0.0" startEvent="default" zOrder="516"/>
    <actor costume="wall" x="-900" y="-420" direction="0.0" heading="0.0" startEvent="default" zOrder="517"/>
    <actor costume="wall" x="-1140" y="-240" direction="0.0" heading="0.0" startEvent="default" zOrder="519"/>
    <actor costume="wall" x="-1200" y="-240" direction="0.0" heading="0.0" startEvent="default" zOrder="520"/>
    <actor costume="wall" x="-1260" y="-240" direction="0.0" heading="0.0" startEvent="default" zOrder="521"/>
    <actor costume="wall" x="-1320" y="-300" direction="0.0" heading="0.0" startEvent="default" zOrder="523"/>
    <actor costume="wall" x="-1320" y="-360" direction="0.0" heading="0.0" startEvent="default" zOrder="524"/>
    <actor costume="wall" x="-1320" y="-420" direction="0.0" heading="0.0" startEvent="default" zOrder="525"/>
    <actor costume="wall" x="-1260" y="-480" direction="0.0" heading="0.0" startEvent="default" zOrder="527"/>
    <actor costume="wall" x="-1200" y="-480" direction="0.0" heading="0.0" startEvent="default" zOrder="528"/>
    <actor costume="wall" x="-1140" y="-480" direction="0.0" heading="0.0" startEvent="default" zOrder="529"/>
    <actor costume="warp" x="-480" y="-180" direction="0.0" heading="0.0" startEvent="default" zOrder="532">
      <property name="exitX" value="0"/>
      <property name="exitY" value="-1"/>
      <property name="scene" value="balloons2"/>
    </actor>
    <actor costume="warp" x="-720" y="-240" direction="0.0" heading="0.0" startEvent="default" zOrder="533">
      <property name="exitX" value="0"/>
      <property name="exitY" value="-1"/>
      <property name="scene" value="balloons3"/>
    </actor>
    <actor costume="warp" x="-960" y="-300" direction="0.0" heading="0.0" startEvent="default" zOrder="534">
      <property name="exitX" value="0"/>
      <property name="exitY" value="-1"/>
      <property name="scene" value="balloons4"/>
    </actor>
    <text text="2" font="Boycott" size="22" color="#ffffff" xAlignment="0.5" yAlignment="0.5" x="-480" y="-180" direction="0.0" heading="0.0" startEvent="default" zOrder="535">
      <makeup classname="uk.co.nickthecoder.itchy.makeup.Shadow">
        <property name="dx" value="2"/>
        <property name="dy" value="-1"/>
        <property name="color" value="#000000ff"/>
      </makeup>
    </text>
    <text text="3" font="Boycott" size="22" color="#ffffff" xAlignment="0.5" yAlignment="0.5" x="-720" y="-240" direction="0.0" heading="0.0" startEvent="default" zOrder="536">
      <makeup classname="uk.co.nickthecoder.itchy.makeup.Shadow">
        <property name="dx" value="2"/>
        <property name="dy" value="-1"/>
        <property name="color" value="#000000ff"/>
      </makeup>
    </text>
    <text text="4" font="Boycott" size="22" color="#ffffff" xAlignment="0.5" yAlignment="0.5" x="-960" y="-300" direction="0.0" heading="0.0" startEvent="default" zOrder="537">
      <makeup classname="uk.co.nickthecoder.itchy.makeup.Shadow">
        <property name="dx" value="2"/>
        <property name="dy" value="-1"/>
        <property name="color" value="#000000ff"/>
      </makeup>
    </text>
    <text text="5" font="Boycott" size="22" color="#ffffff" xAlignment="0.5" yAlignment="0.5" x="-1200" y="-360" direction="0.0" heading="0.0" startEvent="default" zOrder="538">
      <makeup classname="uk.co.nickthecoder.itchy.makeup.Shadow">
        <property name="dx" value="2"/>
        <property name="dy" value="-1"/>
        <property name="color" value="#000000ff"/>
      </makeup>
    </text>
    <actor costume="portcullis" x="-360" y="-180" direction="0.0" heading="0.0" startEvent="default" zOrder="539">
      <property name="text" value="Balloons Stage 1"/>
      <property name="requires" value="balloons"/>
    </actor>
    <actor costume="portcullis" x="-600" y="-240" direction="0.0" heading="0.0" startEvent="default" zOrder="540">
      <property name="text" value="Balloons(2)"/>
      <property name="requires" value="balloons2"/>
    </actor>
    <actor costume="portcullis" x="-840" y="-300" direction="0.0" heading="0.0" startEvent="default" zOrder="541">
      <property name="text" value="Balloons(3)"/>
      <property name="requires" value="balloons3"/>
    </actor>
    <actor costume="portcullis" x="-1080" y="-360" direction="0.0" heading="0.0" startEvent="default" zOrder="542">
      <property name="text" value="Balloons(4)"/>
      <property name="requires" value="balloons4"/>
    </actor>
    <actor costume="wallNW" x="-600" y="-60" direction="0.0" heading="0.0" startEvent="default" zOrder="543"/>
    <actor costume="wallNW" x="-840" y="-120" direction="0.0" heading="0.0" startEvent="default" zOrder="544"/>
    <actor costume="wallNW" x="-1080" y="-180" direction="0.0" heading="0.0" startEvent="default" zOrder="545"/>
    <actor costume="wallNW" x="-1320" y="-240" direction="0.0" heading="0.0" startEvent="default" zOrder="546"/>
    <actor costume="wallSW" x="-1320" y="-480" direction="0.0" heading="0.0" startEvent="default" zOrder="547"/>
    <actor costume="wallSE" x="-1080" y="-480" direction="0.0" heading="0.0" startEvent="default" zOrder="548"/>
    <actor costume="wallSE" x="-840" y="-420" direction="0.0" heading="0.0" startEvent="default" zOrder="549"/>
    <actor costume="wallSE" x="-600" y="-360" direction="0.0" heading="0.0" startEvent="default" zOrder="550"/>
    <actor costume="wallSE" x="-360" y="-300" direction="0.0" heading="0.0" startEvent="default" zOrder="551"/>
  </layer>
</scene>
